{"v":"5.4.4","fr":24,"ip":0,"op":28,"w":48,"h":48,"nm":"eye","ddd":0,"assets":[],"layers":[{"ddd":0,"ind":1,"ty":4,"nm":"Eyelashes","parent":5,"sr":1,"ks":{"o":{"a":0,"k":100,"ix":11},"r":{"a":0,"k":0,"ix":10},"p":{"a":0,"k":[0,0,0],"ix":2},"a":{"a":0,"k":[0,0,0],"ix":1},"s":{"a":0,"k":[100,100,100],"ix":6}},"ao":0,"shapes":[{"ty":"gr","it":[{"ind":0,"ty":"sh","ix":1,"ks":{"a":0,"k":{"i":[[0,0],[0,0]],"o":[[0,0],[0,0]],"v":[[15,5],[21,11]],"c":false},"ix":2},"nm":"Path 1","mn":"ADBE Vector Shape - Group","hd":false},{"ty":"st","c":{"a":0,"k":[0.474509805441,0.333333343267,0.282352954149,1],"ix":3},"o":{"a":0,"k":100,"ix":4},"w":{"a":0,"k":2,"ix":5},"lc":2,"lj":2,"bm":0,"nm":"Stroke 1","mn":"ADBE Vector Graphic - Stroke","hd":false},{"ty":"tr","p":{"a":0,"k":[0,0],"ix":2},"a":{"a":0,"k":[0,0],"ix":1},"s":{"a":0,"k":[100,100],"ix":3},"r":{"a":0,"k":0,"ix":6},"o":{"a":0,"k":100,"ix":7},"sk":{"a":0,"k":0,"ix":4},"sa":{"a":0,"k":0,"ix":5},"nm":"Transform"}],"nm":"Group 1","np":2,"cix":2,"bm":0,"ix":1,"mn":"ADBE Vector Group","hd":false},{"ty":"gr","it":[{"ind":0,"ty":"sh","ix":1,"ks":{"a":0,"k":{"i":[[0,0],[0,0]],"o":[[0,0],[0,0]],"v":[[8.335,9.099],[12,17]],"c":false},"ix":2},"nm":"Path 1","mn":"ADBE Vector Shape - Group","hd":false},{"ty":"st","c":{"a":0,"k":[0.474509805441,0.333333343267,0.282352954149,1],"ix":3},"o":{"a":0,"k":100,"ix":4},"w":{"a":0,"k":2,"ix":5},"lc":2,"lj":2,"bm":0,"nm":"Stroke 1","mn":"ADBE Vector Graphic - Stroke","hd":false},{"ty":"tr","p":{"a":0,"k":[0,0],"ix":2},"a":{"a":0,"k":[0,0],"ix":1},"s":{"a":0,"k":[100,100],"ix":3},"r":{"a":0,"k":0,"ix":6},"o":{"a":0,"k":100,"ix":7},"sk":{"a":0,"k":0,"ix":4},"sa":{"a":0,"k":0,"ix":5},"nm":"Transform"}],"nm":"Group 2","np":2,"cix":2,"bm":0,"ix":2,"mn":"ADBE Vector Group","hd":false},{"ty":"gr","it":[{"ind":0,"ty":"sh","ix":1,"ks":{"a":0,"k":{"i":[[0,0],[0,0]],"o":[[0,0],[0,0]],"v":[[-14.792,4.375],[-21,11]],"c":false},"ix":2},"nm":"Path 1","mn":"ADBE Vector Shape - Group","hd":false},{"ty":"st","c":{"a":0,"k":[0.474509805441,0.333333343267,0.282352954149,1],"ix":3},"o":{"a":0,"k":100,"ix":4},"w":{"a":0,"k":2,"ix":5},"lc":2,"lj":2,"bm":0,"nm":"Stroke 1","mn":"ADBE Vector Graphic - Stroke","hd":false},{"ty":"tr","p":{"a":0,"k":[0,0],"ix":2},"a":{"a":0,"k":[0,0],"ix":1},"s":{"a":0,"k":[100,100],"ix":3},"r":{"a":0,"k":0,"ix":6},"o":{"a":0,"k":100,"ix":7},"sk":{"a":0,"k":0,"ix":4},"sa":{"a":0,"k":0,"ix":5},"nm":"Transform"}],"nm":"Group 3","np":2,"cix":2,"bm":0,"ix":3,"mn":"ADBE Vector Group","hd":false},{"ty":"gr","it":[{"ind":0,"ty":"sh","ix":1,"ks":{"a":0,"k":{"i":[[0,0],[0,0]],"o":[[0,0],[0,0]],"v":[[-7.958,8.75],[-12,17]],"c":false},"ix":2},"nm":"Path 1","mn":"ADBE Vector Shape - Group","hd":false},{"ty":"st","c":{"a":0,"k":[0.474509805441,0.333333343267,0.282352954149,1],"ix":3},"o":{"a":0,"k":100,"ix":4},"w":{"a":0,"k":2,"ix":5},"lc":2,"lj":2,"bm":0,"nm":"Stroke 1","mn":"ADBE Vector Graphic - Stroke","hd":false},{"ty":"tr","p":{"a":0,"k":[0,0],"ix":2},"a":{"a":0,"k":[0,0],"ix":1},"s":{"a":0,"k":[100,100],"ix":3},"r":{"a":0,"k":0,"ix":6},"o":{"a":0,"k":100,"ix":7},"sk":{"a":0,"k":0,"ix":4},"sa":{"a":0,"k":0,"ix":5},"nm":"Transform"}],"nm":"Group 4","np":2,"cix":2,"bm":0,"ix":4,"mn":"ADBE Vector Group","hd":false},{"ty":"gr","it":[{"ind":0,"ty":"sh","ix":1,"ks":{"a":0,"k":{"i":[[0,0],[0,0]],"o":[[0,0],[0,0]],"v":[[0,11],[0,19]],"c":false},"ix":2},"nm":"Path 1","mn":"ADBE Vector Shape - Group","hd":false},{"ty":"st","c":{"a":0,"k":[0.474509805441,0.333333343267,0.282352954149,1],"ix":3},"o":{"a":0,"k":100,"ix":4},"w":{"a":0,"k":2,"ix":5},"lc":2,"lj":2,"bm":0,"nm":"Stroke 1","mn":"ADBE Vector Graphic - Stroke","hd":false},{"ty":"tr","p":{"a":0,"k":[0,0],"ix":2},"a":{"a":0,"k":[0,0],"ix":1},"s":{"a":0,"k":[100,100],"ix":3},"r":{"a":0,"k":0,"ix":6},"o":{"a":0,"k":100,"ix":7},"sk":{"a":0,"k":0,"ix":4},"sa":{"a":0,"k":0,"ix":5},"nm":"Transform"}],"nm":"Group 5","np":2,"cix":2,"bm":0,"ix":5,"mn":"ADBE Vector Group","hd":false},{"ty":"gr","it":[{"ind":0,"ty":"sh","ix":1,"ks":{"a":0,"k":{"i":[[0,0],[0,0]],"o":[[0,0],[0,0]],"v":[[15,5],[21,11]],"c":false},"ix":2},"nm":"Path 1","mn":"ADBE Vector Shape - Group","hd":false},{"ty":"st","c":{"a":0,"k":[0.474509805441,0.333333343267,0.282352954149,1],"ix":3},"o":{"a":0,"k":100,"ix":4},"w":{"a":0,"k":2,"ix":5},"lc":2,"lj":2,"bm":0,"nm":"Stroke 1","mn":"ADBE Vector Graphic - Stroke","hd":false},{"ty":"tr","p":{"a":0,"k":[0,0],"ix":2},"a":{"a":0,"k":[0,0],"ix":1},"s":{"a":0,"k":[100,100],"ix":3},"r":{"a":0,"k":0,"ix":6},"o":{"a":0,"k":100,"ix":7},"sk":{"a":0,"k":0,"ix":4},"sa":{"a":0,"k":0,"ix":5},"nm":"Transform"}],"nm":"Group 6","np":2,"cix":2,"bm":0,"ix":6,"mn":"ADBE Vector Group","hd":false},{"ty":"gr","it":[{"ind":0,"ty":"sh","ix":1,"ks":{"a":0,"k":{"i":[[0,0],[0,0]],"o":[[0,0],[0,0]],"v":[[8.335,9.099],[12,17]],"c":false},"ix":2},"nm":"Path 1","mn":"ADBE Vector Shape - Group","hd":false},{"ty":"st","c":{"a":0,"k":[0.474509805441,0.333333343267,0.282352954149,1],"ix":3},"o":{"a":0,"k":100,"ix":4},"w":{"a":0,"k":2,"ix":5},"lc":2,"lj":2,"bm":0,"nm":"Stroke 1","mn":"ADBE Vector Graphic - Stroke","hd":false},{"ty":"tr","p":{"a":0,"k":[0,0],"ix":2},"a":{"a":0,"k":[0,0],"ix":1},"s":{"a":0,"k":[100,100],"ix":3},"r":{"a":0,"k":0,"ix":6},"o":{"a":0,"k":100,"ix":7},"sk":{"a":0,"k":0,"ix":4},"sa":{"a":0,"k":0,"ix":5},"nm":"Transform"}],"nm":"Group 7","np":2,"cix":2,"bm":0,"ix":7,"mn":"ADBE Vector Group","hd":false},{"ty":"gr","it":[{"ind":0,"ty":"sh","ix":1,"ks":{"a":0,"k":{"i":[[0,0],[0,0]],"o":[[0,0],[0,0]],"v":[[-14.792,4.375],[-21,11]],"c":false},"ix":2},"nm":"Path 1","mn":"ADBE Vector Shape - Group","hd":false},{"ty":"st","c":{"a":0,"k":[0.474509805441,0.333333343267,0.282352954149,1],"ix":3},"o":{"a":0,"k":100,"ix":4},"w":{"a":0,"k":2,"ix":5},"lc":2,"lj":2,"bm":0,"nm":"Stroke 1","mn":"ADBE Vector Graphic - Stroke","hd":false},{"ty":"tr","p":{"a":0,"k":[0,0],"ix":2},"a":{"a":0,"k":[0,0],"ix":1},"s":{"a":0,"k":[100,100],"ix":3},"r":{"a":0,"k":0,"ix":6},"o":{"a":0,"k":100,"ix":7},"sk":{"a":0,"k":0,"ix":4},"sa":{"a":0,"k":0,"ix":5},"nm":"Transform"}],"nm":"Group 8","np":2,"cix":2,"bm":0,"ix":8,"mn":"ADBE Vector Group","hd":false},{"ty":"gr","it":[{"ind":0,"ty":"sh","ix":1,"ks":{"a":0,"k":{"i":[[0,0],[0,0]],"o":[[0,0],[0,0]],"v":[[-7.958,8.75],[-12,17]],"c":false},"ix":2},"nm":"Path 1","mn":"ADBE Vector Shape - Group","hd":false},{"ty":"st","c":{"a":0,"k":[0.474509805441,0.333333343267,0.282352954149,1],"ix":3},"o":{"a":0,"k":100,"ix":4},"w":{"a":0,"k":2,"ix":5},"lc":2,"lj":2,"bm":0,"nm":"Stroke 1","mn":"ADBE Vector Graphic - Stroke","hd":false},{"ty":"tr","p":{"a":0,"k":[0,0],"ix":2},"a":{"a":0,"k":[0,0],"ix":1},"s":{"a":0,"k":[100,100],"ix":3},"r":{"a":0,"k":0,"ix":6},"o":{"a":0,"k":100,"ix":7},"sk":{"a":0,"k":0,"ix":4},"sa":{"a":0,"k":0,"ix":5},"nm":"Transform"}],"nm":"Group 9","np":2,"cix":2,"bm":0,"ix":9,"mn":"ADBE Vector Group","hd":false},{"ty":"gr","it":[{"ind":0,"ty":"sh","ix":1,"ks":{"a":0,"k":{"i":[[0,0],[0,0]],"o":[[0,0],[0,0]],"v":[[0,11],[0,19]],"c":false},"ix":2},"nm":"Path 1","mn":"ADBE Vector Shape - Group","hd":false},{"ty":"st","c":{"a":0,"k":[0.474509805441,0.333333343267,0.282352954149,1],"ix":3},"o":{"a":0,"k":100,"ix":4},"w":{"a":0,"k":2,"ix":5},"lc":2,"lj":2,"bm":0,"nm":"Stroke 1","mn":"ADBE Vector Graphic - Stroke","hd":false},{"ty":"tr","p":{"a":0,"k":[0,0],"ix":2},"a":{"a":0,"k":[0,0],"ix":1},"s":{"a":0,"k":[100,100],"ix":3},"r":{"a":0,"k":0,"ix":6},"o":{"a":0,"k":100,"ix":7},"sk":{"a":0,"k":0,"ix":4},"sa":{"a":0,"k":0,"ix":5},"nm":"Transform"}],"nm":"Group 10","np":2,"cix":2,"bm":0,"ix":10,"mn":"ADBE Vector Group","hd":false},{"ty":"tm","s":{"a":0,"k":0,"ix":1},"e":{"a":1,"k":[{"i":{"x":[0.667],"y":[1]},"o":{"x":[0.167],"y":[0.167]},"t":9,"s":[0],"e":[100]},{"i":{"x":[0.667],"y":[1]},"o":{"x":[0.167],"y":[0]},"t":11,"s":[100],"e":[100]},{"i":{"x":[0.833],"y":[0.833]},"o":{"x":[0.167],"y":[0]},"t":17,"s":[100],"e":[0]},{"t":19}],"ix":2},"o":{"a":0,"k":0,"ix":3},"m":1,"ix":11,"nm":"Trim Paths 1","mn":"ADBE Vector Filter - Trim","hd":false}],"ip":9,"op":19,"st":0,"bm":0},{"ddd":0,"ind":2,"ty":4,"nm":"Eyelash growth line","parent":5,"sr":1,"ks":{"o":{"a":0,"k":100,"ix":11},"r":{"a":0,"k":0,"ix":10},"p":{"a":0,"k":[0,0,0],"ix":2},"a":{"a":0,"k":[0,0,0],"ix":1},"s":{"a":0,"k":[100,100,100],"ix":6}},"ao":0,"shapes":[{"ty":"gr","it":[{"ind":0,"ty":"sh","ix":1,"ks":{"a":1,"k":[{"i":{"x":0.667,"y":1},"o":{"x":0.167,"y":0.167},"t":6,"s":[{"i":[[0,0],[0,0],[8.66,0],[6.497,0],[0,0]],"o":[[0,0],[-5.505,0],[-8.641,0],[0,0],[0,0]],"v":[[19.904,-3],[19.904,-3],[0,-3],[-19.497,-3],[-19.497,-3]],"c":false}],"e":[{"i":[[0,0],[0,0],[8.66,0],[4.156,7.76],[0,0]],"o":[[0,0],[-4.15,7.788],[-8.641,0],[0,0],[0,0]],"v":[[20.505,-3.049],[20.505,-3],[0.118,10],[-20.243,-2.951],[-20.243,-3]],"c":false}]},{"i":{"x":0.667,"y":1},"o":{"x":0.167,"y":0},"t":9,"s":[{"i":[[0,0],[0,0],[8.66,0],[4.156,7.76],[0,0]],"o":[[0,0],[-4.15,7.788],[-8.641,0],[0,0],[0,0]],"v":[[20.505,-3.049],[20.505,-3],[0.118,10],[-20.243,-2.951],[-20.243,-3]],"c":false}],"e":[{"i":[[0,0],[0,0],[8.66,0],[4.156,7.76],[0,0]],"o":[[0,0],[-4.15,7.788],[-8.641,0],[0,0],[0,0]],"v":[[20.505,-3.049],[20.505,-3],[0.118,10],[-20.243,-2.951],[-20.243,-3]],"c":false}]},{"i":{"x":0.833,"y":0.833},"o":{"x":0.167,"y":0},"t":19,"s":[{"i":[[0,0],[0,0],[8.66,0],[4.156,7.76],[0,0]],"o":[[0,0],[-4.15,7.788],[-8.641,0],[0,0],[0,0]],"v":[[20.505,-3.049],[20.505,-3],[0.118,10],[-20.243,-2.951],[-20.243,-3]],"c":false}],"e":[{"i":[[0,0],[0,0],[8.66,0],[6.497,0],[0,0]],"o":[[0,0],[-5.505,0],[-8.641,0],[0,0],[0,0]],"v":[[19.904,-3],[19.904,-3],[0,-3],[-19.497,-3],[-19.497,-3]],"c":false}]},{"t":22}],"ix":2},"nm":"Path 1","mn":"ADBE Vector Shape - Group","hd":false},{"ty":"st","c":{"a":0,"k":[0.474509805441,0.333333343267,0.282352954149,1],"ix":3},"o":{"a":0,"k":100,"ix":4},"w":{"a":0,"k":2,"ix":5},"lc":2,"lj":2,"bm":0,"nm":"Stroke 1","mn":"ADBE Vector Graphic - Stroke","hd":false},{"ty":"tr","p":{"a":0,"k":[0,0],"ix":2},"a":{"a":0,"k":[0,0],"ix":1},"s":{"a":0,"k":[100,100],"ix":3},"r":{"a":0,"k":0,"ix":6},"o":{"a":0,"k":100,"ix":7},"sk":{"a":0,"k":0,"ix":4},"sa":{"a":0,"k":0,"ix":5},"nm":"Transform"}],"nm":"Group 1","np":2,"cix":2,"bm":0,"ix":1,"mn":"ADBE Vector Group","hd":false}],"ip":6,"op":22,"st":0,"bm":0},{"ddd":0,"ind":3,"ty":4,"nm":"Open eye top line 2","parent":5,"sr":1,"ks":{"o":{"a":0,"k":100,"ix":11},"r":{"a":0,"k":0,"ix":10},"p":{"a":0,"k":[-0.072,-10.48,0],"ix":2},"a":{"a":0,"k":[0,0,0],"ix":1},"s":{"a":0,"k":[100,100,100],"ix":6}},"ao":0,"shapes":[{"ty":"gr","it":[{"ind":0,"ty":"sh","ix":1,"ks":{"a":1,"k":[{"i":{"x":0.667,"y":1},"o":{"x":0.167,"y":0.167},"t":22,"s":[{"i":[[0,0],[-9.606,0],[-1.42,0],[0,0],[0,0],[11.837,0],[1,0],[0,0]],"o":[[1.277,0],[9.605,0],[0,0],[0,0],[-1.121,0],[-11.837,0],[0,0],[0,0]],"v":[[-20.591,7.48],[0.006,7.48],[20.492,7.48],[20.577,5.48],[19.072,5.48],[0.005,5.48],[-18.928,5.48],[-20.591,5.48]],"c":true}],"e":[{"i":[[0,0],[-9.606,0],[-0.524,-0.7],[0,0],[0,0],[11.837,0],[0.378,-0.516],[0,0]],"o":[[0.524,-0.7],[9.605,0],[0,0],[0,0],[-0.379,-0.517],[-11.837,0],[0,0],[0,0]],"v":[[-17.969,7.48],[0.005,-3.48],[17.971,7.479],[22.928,7.48],[21.229,5.158],[0.005,-7.48],[-21.226,5.156],[-22.928,7.48]],"c":true}]},{"t":25}],"ix":2},"nm":"Path 1","mn":"ADBE Vector Shape - Group","hd":false},{"ty":"fl","c":{"a":1,"k":[{"i":{"x":[0.667],"y":[1]},"o":{"x":[0.167],"y":[0]},"t":22,"s":[0.474509805441,0.333333343267,0.282352954149,1],"e":[0.564705908298,0.643137276173,0.68235296011,1]},{"t":25}],"ix":4},"o":{"a":0,"k":100,"ix":5},"r":1,"bm":0,"nm":"Fill 1","mn":"ADBE Vector Graphic - Fill","hd":false},{"ty":"tr","p":{"a":0,"k":[0,0],"ix":2},"a":{"a":0,"k":[0,0],"ix":1},"s":{"a":0,"k":[100,100],"ix":3},"r":{"a":0,"k":0,"ix":6},"o":{"a":0,"k":100,"ix":7},"sk":{"a":0,"k":0,"ix":4},"sa":{"a":0,"k":0,"ix":5},"nm":"Transform"}],"nm":"Group 1","np":2,"cix":2,"bm":0,"ix":1,"mn":"ADBE Vector Group","hd":false}],"ip":22,"op":28,"st":22,"bm":0},{"ddd":0,"ind":4,"ty":4,"nm":"Open eye top line","parent":5,"sr":1,"ks":{"o":{"a":0,"k":100,"ix":11},"r":{"a":0,"k":0,"ix":10},"p":{"a":0,"k":[-0.072,-10.48,0],"ix":2},"a":{"a":0,"k":[0,0,0],"ix":1},"s":{"a":0,"k":[100,100,100],"ix":6}},"ao":0,"shapes":[{"ty":"gr","it":[{"ind":0,"ty":"sh","ix":1,"ks":{"a":1,"k":[{"i":{"x":0.833,"y":0.833},"o":{"x":0.333,"y":0},"t":3,"s":[{"i":[[0,0],[-9.606,0],[-0.524,-0.7],[0,0],[0,0],[11.837,0],[0.378,-0.516],[0,0]],"o":[[0.524,-0.7],[9.605,0],[0,0],[0,0],[-0.379,-0.517],[-11.837,0],[0,0],[0,0]],"v":[[-17.969,7.48],[0.005,-3.48],[17.971,7.479],[22.928,7.48],[21.229,5.158],[0.005,-7.48],[-21.226,5.156],[-22.928,7.48]],"c":true}],"e":[{"i":[[0,0],[-9.606,0],[-1.42,0],[0,0],[0,0],[11.837,0],[1,0],[0,0]],"o":[[1.277,0],[9.605,0],[0,0],[0,0],[-1.121,0],[-11.837,0],[0,0],[0,0]],"v":[[-20.591,7.48],[0.006,7.48],[20.492,7.48],[20.577,5.48],[19.072,5.48],[0.005,5.48],[-18.928,5.48],[-20.591,5.48]],"c":true}]},{"t":6}],"ix":2},"nm":"Path 1","mn":"ADBE Vector Shape - Group","hd":false},{"ty":"fl","c":{"a":1,"k":[{"i":{"x":[0.667],"y":[1]},"o":{"x":[0.333],"y":[0]},"t":3,"s":[0.564705908298,0.643137276173,0.68235296011,1],"e":[0.474509805441,0.333333343267,0.282352954149,1]},{"t":6}],"ix":4},"o":{"a":0,"k":100,"ix":5},"r":1,"bm":0,"nm":"Fill 1","mn":"ADBE Vector Graphic - Fill","hd":false},{"ty":"tr","p":{"a":1,"k":[{"i":{"x":0.833,"y":0.833},"o":{"x":0.333,"y":0},"t":3,"s":[0,0],"e":[0,1],"to":[0,0],"ti":[0,0]},{"t":6}],"ix":2},"a":{"a":0,"k":[0,0],"ix":1},"s":{"a":0,"k":[100,100],"ix":3},"r":{"a":0,"k":0,"ix":6},"o":{"a":0,"k":100,"ix":7},"sk":{"a":0,"k":0,"ix":4},"sa":{"a":0,"k":0,"ix":5},"nm":"Transform"}],"nm":"Group 1","np":2,"cix":2,"bm":0,"ix":1,"mn":"ADBE Vector Group","hd":false}],"ip":0,"op":6,"st":0,"bm":0},{"ddd":0,"ind":5,"ty":4,"nm":"Eyelid closing","sr":1,"ks":{"o":{"a":0,"k":100,"ix":11},"r":{"a":0,"k":0,"ix":10},"p":{"a":1,"k":[{"i":{"x":0.667,"y":1},"o":{"x":0.333,"y":0},"t":3,"s":[24,28,0],"e":[24,24,0],"to":[0,0,0],"ti":[0,0,0]},{"i":{"x":0.667,"y":0.667},"o":{"x":0.167,"y":0.167},"t":9,"s":[24,24,0],"e":[24,24,0],"to":[0,0,0],"ti":[0,0,0]},{"i":{"x":0.667,"y":1},"o":{"x":0.167,"y":0},"t":19,"s":[24,24,0],"e":[24,28,0],"to":[0,0,0],"ti":[0,0,0]},{"t":25}],"ix":2},"a":{"a":0,"k":[0,0,0],"ix":1},"s":{"a":0,"k":[100,100,100],"ix":6}},"ao":0,"shapes":[{"ty":"gr","it":[{"ind":0,"ty":"sh","ix":1,"ks":{"a":1,"k":[{"i":{"x":0.833,"y":0.833},"o":{"x":0.333,"y":0},"t":3,"s":[{"i":[[0,0],[8.66,0],[4.033,-7.68],[0,0],[-8.66,0],[-4.156,-7.76]],"o":[[-4.155,-8],[-8.641,0],[0,0],[4.15,-7.788],[8.641,0],[0,0]],"v":[[20.505,-3],[0,-16],[-20.243,-2.951],[-20.243,-3],[0.144,-16],[20.505,-3.049]],"c":true}],"e":[{"i":[[0,0],[8.66,0],[7.243,-0.049],[0,0],[-8.66,0],[-4.156,-7.76]],"o":[[-5.505,0],[-8.641,0],[0,0],[4.15,-7.788],[8.641,0],[0,0]],"v":[[20.505,-3],[0,-3],[-20.243,-2.951],[-20.243,-3],[0.144,-16],[20.505,-3.049]],"c":true}]},{"i":{"x":0.667,"y":1},"o":{"x":0.167,"y":0.167},"t":6,"s":[{"i":[[0,0],[8.66,0],[7.243,-0.049],[0,0],[-8.66,0],[-4.156,-7.76]],"o":[[-5.505,0],[-8.641,0],[0,0],[4.15,-7.788],[8.641,0],[0,0]],"v":[[20.505,-3],[0,-3],[-20.243,-2.951],[-20.243,-3],[0.144,-16],[20.505,-3.049]],"c":true}],"e":[{"i":[[0,0],[8.66,0],[4.156,7.76],[0,0],[-8.66,0],[-4.156,-7.76]],"o":[[-4.15,7.788],[-8.641,0],[0,0],[4.15,-7.788],[8.641,0],[0,0]],"v":[[20.505,-3],[0.118,10],[-20.243,-2.951],[-20.243,-3],[0.144,-16],[20.505,-3.049]],"c":true}]},{"i":{"x":0.667,"y":1},"o":{"x":0.167,"y":0},"t":9,"s":[{"i":[[0,0],[8.66,0],[4.156,7.76],[0,0],[-8.66,0],[-4.156,-7.76]],"o":[[-4.15,7.788],[-8.641,0],[0,0],[4.15,-7.788],[8.641,0],[0,0]],"v":[[20.505,-3],[0.118,10],[-20.243,-2.951],[-20.243,-3],[0.144,-16],[20.505,-3.049]],"c":true}],"e":[{"i":[[0,0],[8.66,0],[4.156,7.76],[0,0],[-8.66,0],[-4.156,-7.76]],"o":[[-4.15,7.788],[-8.641,0],[0,0],[4.15,-7.788],[8.641,0],[0,0]],"v":[[20.505,-3],[0.118,10],[-20.243,-2.951],[-20.243,-3],[0.144,-16],[20.505,-3.049]],"c":true}]},{"i":{"x":0.833,"y":0.833},"o":{"x":0.167,"y":0},"t":19,"s":[{"i":[[0,0],[8.66,0],[4.156,7.76],[0,0],[-8.66,0],[-4.156,-7.76]],"o":[[-4.15,7.788],[-8.641,0],[0,0],[4.15,-7.788],[8.641,0],[0,0]],"v":[[20.505,-3],[0.118,10],[-20.243,-2.951],[-20.243,-3],[0.144,-16],[20.505,-3.049]],"c":true}],"e":[{"i":[[0,0],[8.66,0],[7.243,-0.049],[0,0],[-8.66,0],[-4.156,-7.76]],"o":[[-5.505,0],[-8.641,0],[0,0],[4.15,-7.788],[8.641,0],[0,0]],"v":[[20.505,-3],[0,-3],[-20.243,-2.951],[-20.243,-3],[0.144,-16],[20.505,-3.049]],"c":true}]},{"i":{"x":0.667,"y":1},"o":{"x":0.167,"y":0.167},"t":22,"s":[{"i":[[0,0],[8.66,0],[7.243,-0.049],[0,0],[-8.66,0],[-4.156,-7.76]],"o":[[-5.505,0],[-8.641,0],[0,0],[4.15,-7.788],[8.641,0],[0,0]],"v":[[20.505,-3],[0,-3],[-20.243,-2.951],[-20.243,-3],[0.144,-16],[20.505,-3.049]],"c":true}],"e":[{"i":[[0,0],[8.66,0],[4.033,-7.68],[0,0],[-8.66,0],[-4.156,-7.76]],"o":[[-4.155,-8],[-8.641,0],[0,0],[4.15,-7.788],[8.641,0],[0,0]],"v":[[20.505,-3],[0,-16],[-20.243,-2.951],[-20.243,-3],[0.144,-16],[20.505,-3.049]],"c":true}]},{"t":25}],"ix":2},"nm":"Path 1","mn":"ADBE Vector Shape - Group","hd":false},{"ty":"fl","c":{"a":0,"k":[1,0.717647075653,0.301960796118,1],"ix":4},"o":{"a":0,"k":100,"ix":5},"r":1,"bm":0,"nm":"Fill 1","mn":"ADBE Vector Graphic - Fill","hd":false},{"ty":"tr","p":{"a":0,"k":[0,0],"ix":2},"a":{"a":0,"k":[0,0],"ix":1},"s":{"a":0,"k":[100,100],"ix":3},"r":{"a":0,"k":0,"ix":6},"o":{"a":0,"k":100,"ix":7},"sk":{"a":0,"k":0,"ix":4},"sa":{"a":0,"k":0,"ix":5},"nm":"Transform"}],"nm":"Group 1","np":2,"cix":2,"bm":0,"ix":1,"mn":"ADBE Vector Group","hd":false}],"ip":0,"op":28,"st":0,"bm":0},{"ddd":0,"ind":6,"ty":4,"nm":"Open eye outline 2","parent":5,"sr":1,"ks":{"o":{"a":0,"k":100,"ix":11},"r":{"a":0,"k":0,"ix":10},"p":{"a":0,"k":[0,-4,0],"ix":2},"a":{"a":0,"k":[0,0,0],"ix":1},"s":{"a":0,"k":[100,100,100],"ix":6}},"ao":0,"shapes":[{"ty":"gr","it":[{"ind":0,"ty":"sh","ix":1,"ks":{"a":1,"k":[{"i":{"x":0.667,"y":1},"o":{"x":0.333,"y":0},"t":3,"s":[{"i":[[0,0],[-0.341,-0.467],[0,0],[0,0],[10.323,0],[0.341,0.464],[0,0],[0,0],[-10.335,0]],"o":[[10.326,0],[0,0],[0,0],[-0.341,0.464],[-10.326,0],[0,0],[0,0],[0.341,-0.468],[0,0]],"v":[[-0.066,-11],[18.738,0.452],[19.169,1.044],[18.735,1.634],[-0.066,13],[-18.876,1.633],[-19.31,1.044],[-18.878,0.452],[-0.066,-11]],"c":false}],"e":[{"i":[[0,0],[-0.388,0.504],[0,0],[0,0],[10.323,0],[0.341,0.464],[0,0],[0,0],[-10.335,0]],"o":[[10.326,0],[0,0],[0,0],[-0.341,0.464],[-10.326,0],[0,0],[0,0],[0.363,0.472],[0,0]],"v":[[-0.066,13],[18.735,1.634],[19.169,1.044],[18.735,1.634],[-0.066,13],[-18.876,1.633],[-19.31,1.044],[-18.876,1.633],[-0.066,13]],"c":false}]},{"i":{"x":0.667,"y":1},"o":{"x":0.167,"y":0},"t":9,"s":[{"i":[[0,0],[-0.388,0.504],[0,0],[0,0],[10.323,0],[0.341,0.464],[0,0],[0,0],[-10.335,0]],"o":[[10.326,0],[0,0],[0,0],[-0.341,0.464],[-10.326,0],[0,0],[0,0],[0.363,0.472],[0,0]],"v":[[-0.066,13],[18.735,1.634],[19.169,1.044],[18.735,1.634],[-0.066,13],[-18.876,1.633],[-19.31,1.044],[-18.876,1.633],[-0.066,13]],"c":false}],"e":[{"i":[[0,0],[-0.388,0.504],[0,0],[0,0],[10.323,0],[0.341,0.464],[0,0],[0,0],[-10.335,0]],"o":[[10.326,0],[0,0],[0,0],[-0.341,0.464],[-10.326,0],[0,0],[0,0],[0.363,0.472],[0,0]],"v":[[-0.066,13],[18.735,1.634],[19.169,1.044],[18.735,1.634],[-0.066,13],[-18.876,1.633],[-19.31,1.044],[-18.876,1.633],[-0.066,13]],"c":false}]},{"i":{"x":0.667,"y":1},"o":{"x":0.167,"y":0},"t":19,"s":[{"i":[[0,0],[-0.388,0.504],[0,0],[0,0],[10.323,0],[0.341,0.464],[0,0],[0,0],[-10.335,0]],"o":[[10.326,0],[0,0],[0,0],[-0.341,0.464],[-10.326,0],[0,0],[0,0],[0.363,0.472],[0,0]],"v":[[-0.066,13],[18.735,1.634],[19.169,1.044],[18.735,1.634],[-0.066,13],[-18.876,1.633],[-19.31,1.044],[-18.876,1.633],[-0.066,13]],"c":false}],"e":[{"i":[[0,0],[-0.341,-0.467],[0,0],[0,0],[10.323,0],[0.341,0.464],[0,0],[0,0],[-10.335,0]],"o":[[10.326,0],[0,0],[0,0],[-0.341,0.464],[-10.326,0],[0,0],[0,0],[0.341,-0.468],[0,0]],"v":[[-0.066,-11],[18.738,0.452],[19.169,1.044],[18.735,1.634],[-0.066,13],[-18.876,1.633],[-19.31,1.044],[-18.878,0.452],[-0.066,-11]],"c":false}]},{"t":25}],"ix":2},"nm":"Path 1","mn":"ADBE Vector Shape - Group","hd":false},{"ty":"st","c":{"a":0,"k":[0.811764717102,0.847058832645,0.86274510622,1],"ix":3},"o":{"a":0,"k":100,"ix":4},"w":{"a":0,"k":2,"ix":5},"lc":1,"lj":1,"ml":10,"bm":0,"nm":"Stroke 1","mn":"ADBE Vector Graphic - Stroke","hd":false},{"ty":"tr","p":{"a":0,"k":[0,0],"ix":2},"a":{"a":0,"k":[0,0],"ix":1},"s":{"a":0,"k":[100,100],"ix":3},"r":{"a":0,"k":0,"ix":6},"o":{"a":0,"k":100,"ix":7},"sk":{"a":0,"k":0,"ix":4},"sa":{"a":0,"k":0,"ix":5},"nm":"Transform"}],"nm":"Group 1","np":2,"cix":2,"bm":0,"ix":1,"mn":"ADBE Vector Group","hd":false}],"ip":22,"op":28,"st":0,"bm":0},{"ddd":0,"ind":7,"ty":4,"nm":"Open eye outline 1","parent":5,"sr":1,"ks":{"o":{"a":0,"k":100,"ix":11},"r":{"a":0,"k":0,"ix":10},"p":{"a":0,"k":[0,-4,0],"ix":2},"a":{"a":0,"k":[0,0,0],"ix":1},"s":{"a":0,"k":[100,100,100],"ix":6}},"ao":0,"shapes":[{"ty":"gr","it":[{"ind":0,"ty":"sh","ix":1,"ks":{"a":1,"k":[{"i":{"x":0.667,"y":1},"o":{"x":0.333,"y":0},"t":3,"s":[{"i":[[0,0],[-0.341,-0.467],[0,0],[0,0],[10.323,0],[0.341,0.464],[0,0],[0,0],[-10.335,0]],"o":[[10.326,0],[0,0],[0,0],[-0.341,0.464],[-10.326,0],[0,0],[0,0],[0.341,-0.468],[0,0]],"v":[[-0.066,-11],[18.738,0.452],[19.169,1.044],[18.735,1.634],[-0.066,13],[-18.876,1.633],[-19.31,1.044],[-18.878,0.452],[-0.066,-11]],"c":false}],"e":[{"i":[[0,0],[-0.388,0.504],[0,0],[0,0],[10.323,0],[0.341,0.464],[0,0],[0,0],[-10.335,0]],"o":[[10.326,0],[0,0],[0,0],[-0.341,0.464],[-10.326,0],[0,0],[0,0],[0.363,0.472],[0,0]],"v":[[-0.066,13],[18.735,1.634],[19.169,1.044],[18.735,1.634],[-0.066,13],[-18.876,1.633],[-19.31,1.044],[-18.876,1.633],[-0.066,13]],"c":false}]},{"i":{"x":0.667,"y":1},"o":{"x":0.167,"y":0},"t":9,"s":[{"i":[[0,0],[-0.388,0.504],[0,0],[0,0],[10.323,0],[0.341,0.464],[0,0],[0,0],[-10.335,0]],"o":[[10.326,0],[0,0],[0,0],[-0.341,0.464],[-10.326,0],[0,0],[0,0],[0.363,0.472],[0,0]],"v":[[-0.066,13],[18.735,1.634],[19.169,1.044],[18.735,1.634],[-0.066,13],[-18.876,1.633],[-19.31,1.044],[-18.876,1.633],[-0.066,13]],"c":false}],"e":[{"i":[[0,0],[-0.388,0.504],[0,0],[0,0],[10.323,0],[0.341,0.464],[0,0],[0,0],[-10.335,0]],"o":[[10.326,0],[0,0],[0,0],[-0.341,0.464],[-10.326,0],[0,0],[0,0],[0.363,0.472],[0,0]],"v":[[-0.066,13],[18.735,1.634],[19.169,1.044],[18.735,1.634],[-0.066,13],[-18.876,1.633],[-19.31,1.044],[-18.876,1.633],[-0.066,13]],"c":false}]},{"i":{"x":0.667,"y":1},"o":{"x":0.167,"y":0},"t":19,"s":[{"i":[[0,0],[-0.388,0.504],[0,0],[0,0],[10.323,0],[0.341,0.464],[0,0],[0,0],[-10.335,0]],"o":[[10.326,0],[0,0],[0,0],[-0.341,0.464],[-10.326,0],[0,0],[0,0],[0.363,0.472],[0,0]],"v":[[-0.066,13],[18.735,1.634],[19.169,1.044],[18.735,1.634],[-0.066,13],[-18.876,1.633],[-19.31,1.044],[-18.876,1.633],[-0.066,13]],"c":false}],"e":[{"i":[[0,0],[-0.341,-0.467],[0,0],[0,0],[10.323,0],[0.341,0.464],[0,0],[0,0],[-10.335,0]],"o":[[10.326,0],[0,0],[0,0],[-0.341,0.464],[-10.326,0],[0,0],[0,0],[0.341,-0.468],[0,0]],"v":[[-0.066,-11],[18.738,0.452],[19.169,1.044],[18.735,1.634],[-0.066,13],[-18.876,1.633],[-19.31,1.044],[-18.878,0.452],[-0.066,-11]],"c":false}]},{"t":25}],"ix":2},"nm":"Path 1","mn":"ADBE Vector Shape - Group","hd":false},{"ty":"st","c":{"a":0,"k":[0.811764717102,0.847058832645,0.86274510622,1],"ix":3},"o":{"a":0,"k":100,"ix":4},"w":{"a":0,"k":2,"ix":5},"lc":1,"lj":1,"ml":10,"bm":0,"nm":"Stroke 1","mn":"ADBE Vector Graphic - Stroke","hd":false},{"ty":"tr","p":{"a":0,"k":[0,0],"ix":2},"a":{"a":0,"k":[0,0],"ix":1},"s":{"a":0,"k":[100,100],"ix":3},"r":{"a":0,"k":0,"ix":6},"o":{"a":0,"k":100,"ix":7},"sk":{"a":0,"k":0,"ix":4},"sa":{"a":0,"k":0,"ix":5},"nm":"Transform"}],"nm":"Group 1","np":2,"cix":2,"bm":0,"ix":1,"mn":"ADBE Vector Group","hd":false}],"ip":0,"op":6,"st":0,"bm":0},{"ddd":0,"ind":8,"ty":4,"nm":"Open eye outline rounded","parent":5,"sr":1,"ks":{"o":{"a":0,"k":100,"ix":11},"r":{"a":0,"k":0,"ix":10},"p":{"a":0,"k":[0,-4,0],"ix":2},"a":{"a":0,"k":[0,0,0],"ix":1},"s":{"a":0,"k":[100,100,100],"ix":6}},"ao":0,"shapes":[{"ty":"gr","it":[{"ind":0,"ty":"sh","ix":1,"ks":{"a":1,"k":[{"i":{"x":0.833,"y":0.833},"o":{"x":0.333,"y":0},"t":3,"s":[{"i":[[0,0],[-0.341,-0.467],[0,0],[0,0],[10.323,0],[0.341,0.464],[0,0],[0,0],[-10.335,0]],"o":[[10.326,0],[0,0],[0,0],[-0.341,0.464],[-10.326,0],[0,0],[0,0],[0.341,-0.468],[0,0]],"v":[[-0.066,-11],[18.738,0.452],[19.169,1.044],[18.735,1.634],[-0.066,13],[-18.876,1.633],[-19.31,1.044],[-18.878,0.452],[-0.066,-11]],"c":false}],"e":[{"i":[[0,0],[-0.376,0.252],[0,0],[0,0],[10.323,0],[0.341,0.464],[0,0],[0,0],[-10.335,0]],"o":[[10.326,0],[0,0],[0,0],[-0.341,0.464],[-10.326,0],[0,0],[0,0],[0.358,0.228],[0,0]],"v":[[-0.069,6.215],[18.736,1.327],[19.169,1.044],[18.735,1.634],[-0.066,13],[-18.876,1.633],[-19.31,1.044],[-18.877,1.327],[-0.069,6.215]],"c":false}]},{"i":{"x":0.667,"y":1},"o":{"x":0.167,"y":0.167},"t":7,"s":[{"i":[[0,0],[-0.376,0.252],[0,0],[0,0],[10.323,0],[0.341,0.464],[0,0],[0,0],[-10.335,0]],"o":[[10.326,0],[0,0],[0,0],[-0.341,0.464],[-10.326,0],[0,0],[0,0],[0.358,0.228],[0,0]],"v":[[-0.069,6.215],[18.736,1.327],[19.169,1.044],[18.735,1.634],[-0.066,13],[-18.876,1.633],[-19.31,1.044],[-18.877,1.327],[-0.069,6.215]],"c":false}],"e":[{"i":[[0,0],[-0.388,0.504],[0,0],[0,0],[10.323,0],[0.341,0.464],[0,0],[0,0],[-10.335,0]],"o":[[10.326,0],[0,0],[0,0],[-0.341,0.464],[-10.326,0],[0,0],[0,0],[0.363,0.472],[0,0]],"v":[[-0.066,13],[18.735,1.634],[19.169,1.044],[18.735,1.634],[-0.066,13],[-18.876,1.633],[-19.31,1.044],[-18.876,1.633],[-0.066,13]],"c":false}]},{"i":{"x":0.667,"y":1},"o":{"x":0.167,"y":0},"t":9,"s":[{"i":[[0,0],[-0.388,0.504],[0,0],[0,0],[10.323,0],[0.341,0.464],[0,0],[0,0],[-10.335,0]],"o":[[10.326,0],[0,0],[0,0],[-0.341,0.464],[-10.326,0],[0,0],[0,0],[0.363,0.472],[0,0]],"v":[[-0.066,13],[18.735,1.634],[19.169,1.044],[18.735,1.634],[-0.066,13],[-18.876,1.633],[-19.31,1.044],[-18.876,1.633],[-0.066,13]],"c":false}],"e":[{"i":[[0,0],[-0.388,0.504],[0,0],[0,0],[10.323,0],[0.341,0.464],[0,0],[0,0],[-10.335,0]],"o":[[10.326,0],[0,0],[0,0],[-0.341,0.464],[-10.326,0],[0,0],[0,0],[0.363,0.472],[0,0]],"v":[[-0.066,13],[18.735,1.634],[19.169,1.044],[18.735,1.634],[-0.066,13],[-18.876,1.633],[-19.31,1.044],[-18.876,1.633],[-0.066,13]],"c":false}]},{"i":{"x":0.667,"y":1},"o":{"x":0.167,"y":0},"t":19,"s":[{"i":[[0,0],[-0.388,0.504],[0,0],[0,0],[10.323,0],[0.341,0.464],[0,0],[0,0],[-10.335,0]],"o":[[10.326,0],[0,0],[0,0],[-0.341,0.464],[-10.326,0],[0,0],[0,0],[0.363,0.472],[0,0]],"v":[[-0.066,13],[18.735,1.634],[19.169,1.044],[18.735,1.634],[-0.066,13],[-18.876,1.633],[-19.31,1.044],[-18.876,1.633],[-0.066,13]],"c":false}],"e":[{"i":[[0,0],[-0.341,-0.467],[0,0],[0,0],[10.323,0],[0.341,0.464],[0,0],[0,0],[-10.335,0]],"o":[[10.326,0],[0,0],[0,0],[-0.341,0.464],[-10.326,0],[0,0],[0,0],[0.341,-0.468],[0,0]],"v":[[-0.066,-11],[18.738,0.452],[19.169,1.044],[18.735,1.634],[-0.066,13],[-18.876,1.633],[-19.31,1.044],[-18.878,0.452],[-0.066,-11]],"c":false}]},{"t":25}],"ix":2},"nm":"Path 1","mn":"ADBE Vector Shape - Group","hd":false},{"ty":"st","c":{"a":0,"k":[0.811764717102,0.847058832645,0.86274510622,1],"ix":3},"o":{"a":0,"k":100,"ix":4},"w":{"a":0,"k":2,"ix":5},"lc":1,"lj":2,"bm":0,"nm":"Stroke 1","mn":"ADBE Vector Graphic - Stroke","hd":false},{"ty":"tr","p":{"a":0,"k":[0,0],"ix":2},"a":{"a":0,"k":[0,0],"ix":1},"s":{"a":0,"k":[100,100],"ix":3},"r":{"a":0,"k":0,"ix":6},"o":{"a":0,"k":100,"ix":7},"sk":{"a":0,"k":0,"ix":4},"sa":{"a":0,"k":0,"ix":5},"nm":"Transform"}],"nm":"Group 1","np":2,"cix":2,"bm":0,"ix":1,"mn":"ADBE Vector Group","hd":false}],"ip":6,"op":22,"st":0,"bm":0},{"ddd":0,"ind":9,"ty":4,"nm":"Pupil","parent":5,"sr":1,"ks":{"o":{"a":0,"k":100,"ix":11},"r":{"a":0,"k":0,"ix":10},"p":{"a":0,"k":[0,-4,0],"ix":2},"a":{"a":0,"k":[0,0,0],"ix":1},"s":{"a":0,"k":[100,100,100],"ix":6}},"ao":0,"shapes":[{"ty":"gr","it":[{"ind":0,"ty":"sh","ix":1,"ks":{"a":0,"k":{"i":[[0,2.22],[-2.214,0],[0,-2.213],[2.204,0]],"o":[[0,-2.213],[2.204,0],[0,2.22],[-2.214,0]],"v":[[-4.065,0.999],[-0.065,-3],[3.935,0.999],[-0.065,5]],"c":true},"ix":2},"nm":"Path 1","mn":"ADBE Vector Shape - Group","hd":false},{"ty":"fl","c":{"a":0,"k":[0,0.376470595598,0.392156869173,1],"ix":4},"o":{"a":0,"k":100,"ix":5},"r":1,"bm":0,"nm":"Fill 1","mn":"ADBE Vector Graphic - Fill","hd":false},{"ty":"tr","p":{"a":0,"k":[0,0],"ix":2},"a":{"a":0,"k":[0,0],"ix":1},"s":{"a":0,"k":[100,100],"ix":3},"r":{"a":0,"k":0,"ix":6},"o":{"a":0,"k":100,"ix":7},"sk":{"a":0,"k":0,"ix":4},"sa":{"a":0,"k":0,"ix":5},"nm":"Transform"}],"nm":"Group 1","np":2,"cix":2,"bm":0,"ix":1,"mn":"ADBE Vector Group","hd":false},{"ty":"gr","it":[{"ind":0,"ty":"sh","ix":1,"ks":{"a":0,"k":{"i":[[0,4.977],[-4.966,0],[0,-4.971],[4.968,0]],"o":[[0,-4.971],[4.968,0],[0,4.977],[-4.967,0]],"v":[[-9.065,0.994],[-0.065,-8],[8.935,0.994],[-0.065,10]],"c":true},"ix":2},"nm":"Path 1","mn":"ADBE Vector Shape - Group","hd":false},{"ty":"fl","c":{"a":0,"k":[0,0.674509823322,0.75686275959,1],"ix":4},"o":{"a":0,"k":100,"ix":5},"r":1,"bm":0,"nm":"Fill 1","mn":"ADBE Vector Graphic - Fill","hd":false},{"ty":"tr","p":{"a":0,"k":[0,0],"ix":2},"a":{"a":0,"k":[0,0],"ix":1},"s":{"a":0,"k":[100,100],"ix":3},"r":{"a":0,"k":0,"ix":6},"o":{"a":0,"k":100,"ix":7},"sk":{"a":0,"k":0,"ix":4},"sa":{"a":0,"k":0,"ix":5},"nm":"Transform"}],"nm":"Group 2","np":2,"cix":2,"bm":0,"ix":2,"mn":"ADBE Vector Group","hd":false}],"ip":0,"op":28,"st":0,"bm":0},{"ddd":0,"ind":10,"ty":4,"nm":"Eye white","parent":5,"sr":1,"ks":{"o":{"a":0,"k":100,"ix":11},"r":{"a":0,"k":0,"ix":10},"p":{"a":0,"k":[-0.07,-3,0],"ix":2},"a":{"a":0,"k":[0,0,0],"ix":1},"s":{"a":0,"k":[100,100,100],"ix":6}},"ao":0,"shapes":[{"ty":"gr","it":[{"ind":0,"ty":"sh","ix":1,"ks":{"a":0,"k":{"i":[[0,0],[10.334,0],[0.341,-0.468],[0,0],[0,0],[-10.332,0],[-0.341,0.464],[0,0]],"o":[[-0.341,-0.468],[-10.333,0],[0,0],[0,0],[0.341,0.464],[10.332,0],[0,0],[0,0]],"v":[[18.808,-0.548],[0.004,-12],[-18.807,-0.549],[-19.239,0.043],[-18.805,0.633],[0.004,12],[18.806,0.633],[19.239,0.043]],"c":true},"ix":2},"nm":"Path 1","mn":"ADBE Vector Shape - Group","hd":false},{"ty":"fl","c":{"a":0,"k":[1,1,1,1],"ix":4},"o":{"a":0,"k":100,"ix":5},"r":1,"bm":0,"nm":"Fill 1","mn":"ADBE Vector Graphic - Fill","hd":false},{"ty":"tr","p":{"a":0,"k":[0,0],"ix":2},"a":{"a":0,"k":[0,0],"ix":1},"s":{"a":0,"k":[100,100],"ix":3},"r":{"a":0,"k":0,"ix":6},"o":{"a":0,"k":100,"ix":7},"sk":{"a":0,"k":0,"ix":4},"sa":{"a":0,"k":0,"ix":5},"nm":"Transform"}],"nm":"Group 1","np":2,"cix":2,"bm":0,"ix":1,"mn":"ADBE Vector Group","hd":false}],"ip":0,"op":28,"st":0,"bm":0}],"markers":[]}